README.txt
setup.py
hgmonitor/__init__.py
hgmonitor/hglib.py
hgmonitor/hgmonlib.py
hgmonitor.egg-info/PKG-INFO
hgmonitor.egg-info/SOURCES.txt
hgmonitor.egg-info/dependency_links.txt
hgmonitor.egg-info/top_level.txt