Metadata-Version: 1.1
Name: hgmonitor
Version: 0.5
Summary: mercurial repository monitoring and handling as a group
Home-page: http://bitbucket.org/jbmohler/hg-monitor
Author: Joel B. Mohler
Author-email: joel@kiwistrawberry.us
License: GPLv2+
Platform: UNKNOWN
Classifier: Development Status :: 4 - Beta
Classifier: Intended Audience :: Developers
Classifier: License :: OSI Approved :: GNU General Public License (GPL)
Classifier: Programming Language :: Python :: 2
Classifier: Topic :: Software Development :: Libraries
Classifier: Topic :: Software Development :: Libraries :: Python Modules
Classifier: Topic :: Software Development :: Version Control
Classifier: Operating System :: OS Independent
